scs_analysis/__init__.py
scs_analysis/alert.py
scs_analysis/alert_status.py
scs_analysis/aws_byline.py
scs_analysis/aws_client_auth.py
scs_analysis/aws_mqtt_client.py
scs_analysis/aws_topic_history.py
scs_analysis/aws_topic_origin.py
scs_analysis/aws_topic_publisher.py
scs_analysis/aws_upload_interval.py
scs_analysis/baseline.py
scs_analysis/baseline_conf.py
scs_analysis/client_traffic.py
scs_analysis/cognito_devices.py
scs_analysis/cognito_email.py
scs_analysis/cognito_user_credentials.py
scs_analysis/cognito_user_identity.py
scs_analysis/cognito_users.py
scs_analysis/configuration_csv.py
scs_analysis/configuration_monitor.py
scs_analysis/configuration_monitor_check.py
scs_analysis/configuration_report.py
scs_analysis/csv_collation_summary.py
scs_analysis/csv_collator.py
scs_analysis/csv_join.py
scs_analysis/csv_reader.py
scs_analysis/csv_segmentor.py
scs_analysis/csv_writer.py
scs_analysis/device_controller.py
scs_analysis/device_monitor.py
scs_analysis/device_monitor_status.py
scs_analysis/gas_response_summary.py
scs_analysis/histo_chart.py
scs_analysis/localised_datetime.py
scs_analysis/monitor_auth.py
scs_analysis/multi_chart.py
scs_analysis/node.py
scs_analysis/organisation_devices.py
scs_analysis/organisation_path_roots.py
scs_analysis/organisation_user_paths.py
scs_analysis/organisation_users.py
scs_analysis/organisations.py
scs_analysis/sample_aggregate.py
scs_analysis/sample_average.py
scs_analysis/sample_collator.py
scs_analysis/sample_distance.py
scs_analysis/sample_duplicates.py
scs_analysis/sample_error.py
scs_analysis/sample_gas_concentration.py
scs_analysis/sample_gas_density.py
scs_analysis/sample_interval.py
scs_analysis/sample_iso_8601.py
scs_analysis/sample_localize.py
scs_analysis/sample_low_pass.py
scs_analysis/sample_max.py
scs_analysis/sample_mdape.py
scs_analysis/sample_median.py
scs_analysis/sample_midpoint.py
scs_analysis/sample_min.py
scs_analysis/sample_noise.py
scs_analysis/sample_nullify.py
scs_analysis/sample_paths.py
scs_analysis-3.12.1.dist-info/LICENSE
scs_analysis-3.12.1.dist-info/METADATA
scs_analysis-3.12.1.dist-info/WHEEL
scs_analysis-3.12.1.dist-info/top_level.txt
scs_analysis-3.12.1.dist-info/RECORD
