Metadata-Version: 2.1
Name: scs-analysis
Version: 3.12.1
Summary: Information management and analysis utilities for South Coast Science data consumers
Home-page: https://github.com/south-coast-science/scs_analysis
Author: South Coast Science
Author-email: contact@southcoastscience.com
Platform: any
Classifier: Programming Language :: Python :: 3
Classifier: Programming Language :: Python :: 3.11
Classifier: License :: OSI Approved :: MIT License
Classifier: Operating System :: MacOS :: MacOS X
Classifier: Operating System :: Microsoft :: Windows :: Windows 10
Classifier: Operating System :: POSIX
Requires-Python: >3.6
License-File: LICENSE
Requires-Dist: AWSIoTPythonSDK ~=1.4.9
Requires-Dist: gnureadline ~=8.1.2
Requires-Dist: matplotlib ~=3.3
Requires-Dist: paho-mqtt ~=1.5.0
Requires-Dist: pycryptodome ~=3.15.0
Requires-Dist: pypandoc ~=1.5
Requires-Dist: pysftp ~=0.2.9
Requires-Dist: pytz ~=2020.1
Requires-Dist: requests ~=2.28.2
Requires-Dist: scipy ~=1.5
Requires-Dist: setuptools ~=50.3.0
Requires-Dist: tzlocal ~=2.1
Requires-Dist: scs-core ~=3.16.3
Requires-Dist: scs-host-posix ~=3.3.1
Provides-Extra: dev
Requires-Dist: pypandoc ; extra == 'dev'
